{
  "kind": "collectionType",
  "collectionName": "carts",
  "info": {
    "singularName": "cart",
    "pluralName": "carts",
    "displayName": "Cart"
  },
  "options": {
    "draftAndPublish": true
  },
  "pluginOptions": {},
  "attributes": {
    "users_id": {
      "type": "relation",
      "relation": "oneToOne",
      "target": "plugin::users-permissions.user",
      "mappedBy": "cart"
    },
    "cart_items": {
      "type": "relation",
      "relation": "oneToMany",
      "target": "api::cart-item.cart-item",
      "mappedBy": "cart"
    }
  }
}
